uipath_connectors/salesforce_slack/__init__.py
uipath_connectors/salesforce_slack/client.py
uipath_connectors/salesforce_slack/errors.py
uipath_connectors/salesforce_slack/py.typed
uipath_connectors/salesforce_slack/types.py
uipath_connectors/salesforce_slack/api/__init__.py
uipath_connectors/salesforce_slack/api/add_users_usergroups/__init__.py
uipath_connectors/salesforce_slack/api/add_users_usergroups/add_users_to_usergroup.py
uipath_connectors/salesforce_slack/api/channel_archive/__init__.py
uipath_connectors/salesforce_slack/api/channel_archive/channel_archive.py
uipath_connectors/salesforce_slack/api/conversations/__init__.py
uipath_connectors/salesforce_slack/api/conversations/create_channel.py
uipath_connectors/salesforce_slack/api/conversations_info_get/__init__.py
uipath_connectors/salesforce_slack/api/conversations_info_get/get_conversation_info.py
uipath_connectors/salesforce_slack/api/conversations_invite_post/__init__.py
uipath_connectors/salesforce_slack/api/conversations_invite_post/invite_to_channel.py
uipath_connectors/salesforce_slack/api/conversations_join_post/__init__.py
uipath_connectors/salesforce_slack/api/conversations_join_post/conversations_join.py
uipath_connectors/salesforce_slack/api/conversations_kick_post/__init__.py
uipath_connectors/salesforce_slack/api/conversations_kick_post/remove_from_channel.py
uipath_connectors/salesforce_slack/api/conversations_open/__init__.py
uipath_connectors/salesforce_slack/api/conversations_open/conversations_open.py
uipath_connectors/salesforce_slack/api/send_button_response/__init__.py
uipath_connectors/salesforce_slack/api/send_button_response/send_button_response.py
uipath_connectors/salesforce_slack/api/send_files_to_channel/__init__.py
uipath_connectors/salesforce_slack/api/send_files_to_channel/upload_file.py
uipath_connectors/salesforce_slack/api/send_message_to_channel_v2/__init__.py
uipath_connectors/salesforce_slack/api/send_message_to_channel_v2/send_message.py
uipath_connectors_salesforce_slack-2.10.28.dev12.dist-info/METADATA
uipath_connectors_salesforce_slack-2.10.28.dev12.dist-info/WHEEL
uipath_connectors_salesforce_slack-2.10.28.dev12.dist-info/entry_points.txt
uipath_connectors_salesforce_slack-2.10.28.dev12.dist-info/top_level.txt
uipath_connectors_salesforce_slack-2.10.28.dev12.dist-info/RECORD
